{
  "company_id": "moldasig_s_a",
  "company_name": "MOLDASIG S.A.",
  "is_reference": false,
  "premiums": [
    {
      "cell_id": "A1_CH_PF_AGE_LT23_EXP_LT2",
      "value": 3191.11
    },
    {
      "cell_id": "A1_CH_PF_AGE_LT23_EXP_GE2",
      "value": 2604.06
    },
    {
      "cell_id": "A1_CH_PF_AGE_GE23_EXP_LT2",
      "value": 2054.4
    },
    {
      "cell_id": "A1_CH_PF_AGE_GE23_EXP_GE2",
      "value": 1931.14
    },
    {
      "cell_id": "A1_CH_PJ",
      "value": 3646.57
    },
    {
      "cell_id": "A1_AL_PF_AGE_LT23_EXP_LT2",
      "value": 1756.35
    },
    {
      "cell_id": "A1_AL_PF_AGE_LT23_EXP_GE2",
      "value": 1433.24
    },
    {
      "cell_id": "A1_AL_PF_AGE_GE23_EXP_LT2",
      "value": 1059.81
    },
    {
      "cell_id": "A1_AL_PF_AGE_GE23_EXP_GE2",
      "value": 996.22
    },
    {
      "cell_id": "A1_AL_PJ",
      "value": 1881.17
    },
    {
      "cell_id": "A2_CH_PF_AGE_LT23_EXP_LT2",
      "value": 3346.14
    },
    {
      "cell_id": "A2_CH_PF_AGE_LT23_EXP_GE2",
      "value": 2481.91
    },
    {
      "cell_id": "A2_CH_PF_AGE_GE23_EXP_LT2",
      "value": 2215.99
    },
    {
      "cell_id": "A2_CH_PF_AGE_GE23_EXP_GE2",
      "value": 2083.03
    },
    {
      "cell_id": "A2_CH_PJ",
      "value": 3933.38
    },
    {
      "cell_id": "A2_AL_PF_AGE_LT23_EXP_LT2",
      "value": 1726.18
    },
    {
      "cell_id": "A2_AL_PF_AGE_LT23_EXP_GE2",
      "value": 1329.81
    },
    {
      "cell_id": "A2_AL_PF_AGE_GE23_EXP_LT2",
      "value": 1143.17
    },
    {
      "cell_id": "A2_AL_PF_AGE_GE23_EXP_GE2",
      "value": 1074.58
    },
    {
      "cell_id": "A2_AL_PJ",
      "value": 2029.12
    },
    {
      "cell_id": "A3_CH_PF_AGE_LT23_EXP_LT2",
      "value": 3624.99
    },
    {
      "cell_id": "A3_CH_PF_AGE_LT23_EXP_GE2",
      "value": 2688.73
    },
    {
      "cell_id": "A3_CH_PF_AGE_GE23_EXP_LT2",
      "value": 2400.65
    },
    {
      "cell_id": "A3_CH_PF_AGE_GE23_EXP_GE2",
      "value": 2256.61
    },
    {
      "cell_id": "A3_CH_PJ",
      "value": 4261.16
    },
    {
      "cell_id": "A3_AL_PF_AGE_LT23_EXP_LT2",
      "value": 1870.03
    },
    {
      "cell_id": "A3_AL_PF_AGE_LT23_EXP_GE2",
      "value": 1387.04
    },
    {
      "cell_id": "A3_AL_PF_AGE_GE23_EXP_LT2",
      "value": 1238.43
    },
    {
      "cell_id": "A3_AL_PF_AGE_GE23_EXP_GE2",
      "value": 1164.13
    },
    {
      "cell_id": "A3_AL_PJ",
      "value": 2198.22
    },
    {
      "cell_id": "A4_CH_PF_AGE_LT23_EXP_LT2",
      "value": 3717.47
    },
    {
      "cell_id": "A4_CH_PF_AGE_LT23_EXP_GE2",
      "value": 3033.6
    },
    {
      "cell_id": "A4_CH_PF_AGE_GE23_EXP_LT2",
      "value": 2377.57
    },
    {
      "cell_id": "A4_CH_PF_AGE_GE23_EXP_GE2",
      "value": 2234.92
    },
    {
      "cell_id": "A4_CH_PJ",
      "value": 4220.19
    },
    {
      "cell_id": "A4_AL_PF_AGE_LT23_EXP_LT2",
      "value": 2046.05
    },
    {
      "cell_id": "A4_AL_PF_AGE_LT23_EXP_GE2",
      "value": 1669.66
    },
    {
      "cell_id": "A4_AL_PF_AGE_GE23_EXP_LT2",
      "value": 1226.52
    },
    {
      "cell_id": "A4_AL_PF_AGE_GE23_EXP_GE2",
      "value": 1152.93
    },
    {
      "cell_id": "A4_AL_PJ",
      "value": 2177.08
    },
    {
      "cell_id": "A5_CH_PF_AGE_LT23_EXP_LT2",
      "value": 3881.96
    },
    {
      "cell_id": "A5_CH_PF_AGE_LT23_EXP_GE2",
      "value": 3167.83
    },
    {
      "cell_id": "A5_CH_PF_AGE_GE23_EXP_LT2",
      "value": 2239.07
    },
    {
      "cell_id": "A5_CH_PF_AGE_GE23_EXP_GE2",
      "value": 2104.73
    },
    {
      "cell_id": "A5_CH_PJ",
      "value": 3974.35
    },
    {
      "cell_id": "A5_AL_PF_AGE_LT23_EXP_LT2",
      "value": 2136.59
    },
    {
      "cell_id": "A5_AL_PF_AGE_LT23_EXP_GE2",
      "value": 1743.53
    },
    {
      "cell_id": "A5_AL_PF_AGE_GE23_EXP_LT2",
      "value": 1155.08
    },
    {
      "cell_id": "A5_AL_PF_AGE_GE23_EXP_GE2",
      "value": 1085.77
    },
    {
      "cell_id": "A5_AL_PJ",
      "value": 2050.26
    },
    {
      "cell_id": "A6_CH_PF_AGE_LT23_EXP_LT2",
      "value": 4775.22
    },
    {
      "cell_id": "A6_CH_PF_AGE_LT23_EXP_GE2",
      "value": 3570.52
    },
    {
      "cell_id": "A6_CH_PF_AGE_GE23_EXP_LT2",
      "value": 3162.4
    },
    {
      "cell_id": "A6_CH_PF_AGE_GE23_EXP_GE2",
      "value": 2972.65
    },
    {
      "cell_id": "A6_CH_PJ",
      "value": 5613.26
    },
    {
      "cell_id": "A6_AL_PF_AGE_LT23_EXP_LT2",
      "value": 2463.41
    },
    {
      "cell_id": "A6_AL_PF_AGE_LT23_EXP_GE2",
      "value": 1965.17
    },
    {
      "cell_id": "A6_AL_PF_AGE_GE23_EXP_LT2",
      "value": 1631.4
    },
    {
      "cell_id": "A6_AL_PF_AGE_GE23_EXP_GE2",
      "value": 1533.51
    },
    {
      "cell_id": "A6_AL_PJ",
      "value": 2895.73
    },
    {
      "cell_id": "A7_CH_PJ",
      "value": 3646.57
    },
    {
      "cell_id": "A7_AL_PJ",
      "value": 1881.17
    },
    {
      "cell_id": "A8_CH_PF_AGE_LT23_EXP_LT2",
      "value": 4949.5
    },
    {
      "cell_id": "A8_CH_PF_AGE_LT23_EXP_GE2",
      "value": 3812.13
    },
    {
      "cell_id": "A8_CH_PF_AGE_GE23_EXP_LT2",
      "value": 3277.81
    },
    {
      "cell_id": "A8_CH_PF_AGE_GE23_EXP_GE2",
      "value": 3081.15
    },
    {
      "cell_id": "A8_CH_PJ",
      "value": 5818.12
    },
    {
      "cell_id": "A8_AL_PF_AGE_LT23_EXP_LT2",
      "value": 2571.14
    },
    {
      "cell_id": "A8_AL_PF_AGE_LT23_EXP_GE2",
      "value": 2098.15
    },
    {
      "cell_id": "A8_AL_PF_AGE_GE23_EXP_LT2",
      "value": 1690.94
    },
    {
      "cell_id": "A8_AL_PF_AGE_GE23_EXP_GE2",
      "value": 1589.48
    },
    {
      "cell_id": "A8_AL_PJ",
      "value": 3001.41
    },
    {
      "cell_id": "B1_CH_PF_AGE_LT23_EXP_LT2",
      "value": 3158.21
    },
    {
      "cell_id": "B1_CH_PF_AGE_LT23_EXP_GE2",
      "value": 2577.22
    },
    {
      "cell_id": "B1_CH_PF_AGE_GE23_EXP_LT2",
      "value": 1653.59
    },
    {
      "cell_id": "B1_CH_PF_AGE_GE23_EXP_GE2",
      "value": 998.11
    },
    {
      "cell_id": "B1_CH_PJ",
      "value": 2779.6
    },
    {
      "cell_id": "B1_AL_PF_AGE_LT23_EXP_LT2",
      "value": 1738.24
    },
    {
      "cell_id": "B1_AL_PF_AGE_LT23_EXP_GE2",
      "value": 1418.47
    },
    {
      "cell_id": "B1_AL_PF_AGE_GE23_EXP_LT2",
      "value": 910.12
    },
    {
      "cell_id": "B1_AL_PF_AGE_GE23_EXP_GE2",
      "value": 549.35
    },
    {
      "cell_id": "B1_AL_PJ",
      "value": 1529.86
    },
    {
      "cell_id": "B2_CH_PF_AGE_LT23_EXP_LT2",
      "value": 5132.09
    },
    {
      "cell_id": "B2_CH_PF_AGE_LT23_EXP_GE2",
      "value": 4187.98
    },
    {
      "cell_id": "B2_CH_PF_AGE_GE23_EXP_LT2",
      "value": 2687.08
    },
    {
      "cell_id": "B2_CH_PF_AGE_GE23_EXP_GE2",
      "value": 1621.93
    },
    {
      "cell_id": "B2_CH_PJ",
      "value": 4516.85
    },
    {
      "cell_id": "B2_AL_PF_AGE_LT23_EXP_LT2",
      "value": 2824.64
    },
    {
      "cell_id": "B2_AL_PF_AGE_LT23_EXP_GE2",
      "value": 2305.01
    },
    {
      "cell_id": "B2_AL_PF_AGE_GE23_EXP_LT2",
      "value": 1478.94
    },
    {
      "cell_id": "B2_AL_PF_AGE_GE23_EXP_GE2",
      "value": 892.69
    },
    {
      "cell_id": "B2_AL_PJ",
      "value": 2486.02
    },
    {
      "cell_id": "B3_CH_PF_AGE_LT23_EXP_LT2",
      "value": 10264.18
    },
    {
      "cell_id": "B3_CH_PF_AGE_LT23_EXP_GE2",
      "value": 8375.96
    },
    {
      "cell_id": "B3_CH_PF_AGE_GE23_EXP_LT2",
      "value": 5374.17
    },
    {
      "cell_id": "B3_CH_PF_AGE_GE23_EXP_GE2",
      "value": 3243.87
    },
    {
      "cell_id": "B3_CH_PJ",
      "value": 9033.7
    },
    {
      "cell_id": "B3_AL_PF_AGE_LT23_EXP_LT2",
      "value": 5649.28
    },
    {
      "cell_id": "B3_AL_PF_AGE_LT23_EXP_GE2",
      "value": 4610.02
    },
    {
      "cell_id": "B3_AL_PF_AGE_GE23_EXP_LT2",
      "value": 2957.88
    },
    {
      "cell_id": "B3_AL_PF_AGE_GE23_EXP_GE2",
      "value": 1785.38
    },
    {
      "cell_id": "B3_AL_PJ",
      "value": 4972.04
    },
    {
      "cell_id": "B4_CH_PJ",
      "value": 24901
    },
    {
      "cell_id": "B4_AL_PJ",
      "value": 12845.76
    },
    {
      "cell_id": "C1_CH_PF_AGE_LT23_EXP_LT2",
      "value": 1673.07
    },
    {
      "cell_id": "C1_CH_PF_AGE_LT23_EXP_GE2",
      "value": 1240.95
    },
    {
      "cell_id": "C1_CH_PF_AGE_GE23_EXP_LT2",
      "value": 1107.99
    },
    {
      "cell_id": "C1_CH_PF_AGE_GE23_EXP_GE2",
      "value": 1041.51
    },
    {
      "cell_id": "C1_CH_PJ",
      "value": 1384.99
    },
    {
      "cell_id": "C1_AL_PF_AGE_LT23_EXP_LT2",
      "value": 863.09
    },
    {
      "cell_id": "C1_AL_PF_AGE_LT23_EXP_GE2",
      "value": 640.17
    },
    {
      "cell_id": "C1_AL_PF_AGE_GE23_EXP_LT2",
      "value": 571.58
    },
    {
      "cell_id": "C1_AL_PF_AGE_GE23_EXP_GE2",
      "value": 537.29
    },
    {
      "cell_id": "C1_AL_PJ",
      "value": 714.48
    },
    {
      "cell_id": "C2_CH_PF_AGE_LT23_EXP_LT2",
      "value": 1254.8
    },
    {
      "cell_id": "C2_CH_PF_AGE_LT23_EXP_GE2",
      "value": 930.71
    },
    {
      "cell_id": "C2_CH_PF_AGE_GE23_EXP_LT2",
      "value": 831
    },
    {
      "cell_id": "C2_CH_PF_AGE_GE23_EXP_GE2",
      "value": 781.14
    },
    {
      "cell_id": "C2_CH_PJ",
      "value": 1038.74
    },
    {
      "cell_id": "C2_AL_PF_AGE_LT23_EXP_LT2",
      "value": 647.32
    },
    {
      "cell_id": "C2_AL_PF_AGE_LT23_EXP_GE2",
      "value": 480.13
    },
    {
      "cell_id": "C2_AL_PF_AGE_GE23_EXP_LT2",
      "value": 428.69
    },
    {
      "cell_id": "C2_AL_PF_AGE_GE23_EXP_GE2",
      "value": 402.97
    },
    {
      "cell_id": "C2_AL_PJ",
      "value": 535.86
    },
    {
      "cell_id": "C3_CH_PF_AGE_LT23_EXP_LT2",
      "value": 627.4
    },
    {
      "cell_id": "C3_CH_PF_AGE_LT23_EXP_GE2",
      "value": 483.23
    },
    {
      "cell_id": "C3_CH_PF_AGE_GE23_EXP_LT2",
      "value": 415.5
    },
    {
      "cell_id": "C3_CH_PF_AGE_GE23_EXP_GE2",
      "value": 390.57
    },
    {
      "cell_id": "C3_CH_PJ",
      "value": 519.37
    },
    {
      "cell_id": "C3_AL_PF_AGE_LT23_EXP_LT2",
      "value": 325.92
    },
    {
      "cell_id": "C3_AL_PF_AGE_LT23_EXP_GE2",
      "value": 265.96
    },
    {
      "cell_id": "C3_AL_PF_AGE_GE23_EXP_LT2",
      "value": 214.34
    },
    {
      "cell_id": "C3_AL_PF_AGE_GE23_EXP_GE2",
      "value": 201.48
    },
    {
      "cell_id": "C3_AL_PJ",
      "value": 267.93
    },
    {
      "cell_id": "D1_CH_PF_AGE_LT23_EXP_LT2",
      "value": 3322.7
    },
    {
      "cell_id": "D1_CH_PF_AGE_LT23_EXP_GE2",
      "value": 2711.45
    },
    {
      "cell_id": "D1_CH_PF_AGE_GE23_EXP_LT2",
      "value": 2146.74
    },
    {
      "cell_id": "D1_CH_PF_AGE_GE23_EXP_GE2",
      "value": 2017.93
    },
    {
      "cell_id": "D1_CH_PJ",
      "value": 2683.42
    },
    {
      "cell_id": "D1_AL_PF_AGE_LT23_EXP_LT2",
      "value": 1828.77
    },
    {
      "cell_id": "D1_AL_PF_AGE_LT23_EXP_GE2",
      "value": 1492.35
    },
    {
      "cell_id": "D1_AL_PF_AGE_GE23_EXP_LT2",
      "value": 1107.44
    },
    {
      "cell_id": "D1_AL_PF_AGE_GE23_EXP_GE2",
      "value": 1041
    },
    {
      "cell_id": "D1_AL_PJ",
      "value": 1384.31
    },
    {
      "cell_id": "D2_CH_PF_AGE_LT23_EXP_LT2",
      "value": 4342.54
    },
    {
      "cell_id": "D2_CH_PF_AGE_LT23_EXP_GE2",
      "value": 3543.67
    },
    {
      "cell_id": "D2_CH_PF_AGE_GE23_EXP_LT2",
      "value": 2816.15
    },
    {
      "cell_id": "D2_CH_PF_AGE_GE23_EXP_GE2",
      "value": 2647.18
    },
    {
      "cell_id": "D2_CH_PJ",
      "value": 3520.19
    },
    {
      "cell_id": "D2_AL_PF_AGE_LT23_EXP_LT2",
      "value": 2390.08
    },
    {
      "cell_id": "D2_AL_PF_AGE_LT23_EXP_GE2",
      "value": 1950.39
    },
    {
      "cell_id": "D2_AL_PF_AGE_GE23_EXP_LT2",
      "value": 1452.78
    },
    {
      "cell_id": "D2_AL_PF_AGE_GE23_EXP_GE2",
      "value": 1365.61
    },
    {
      "cell_id": "D2_AL_PJ",
      "value": 1815.97
    },
    {
      "cell_id": "D3_CH_PF_AGE_LT23_EXP_LT2",
      "value": 5362.37
    },
    {
      "cell_id": "D3_CH_PF_AGE_LT23_EXP_GE2",
      "value": 4375.9
    },
    {
      "cell_id": "D3_CH_PF_AGE_GE23_EXP_LT2",
      "value": 3300.9
    },
    {
      "cell_id": "D3_CH_PF_AGE_GE23_EXP_GE2",
      "value": 3102.84
    },
    {
      "cell_id": "D3_CH_PJ",
      "value": 4126.12
    },
    {
      "cell_id": "D3_AL_PF_AGE_LT23_EXP_LT2",
      "value": 2951.38
    },
    {
      "cell_id": "D3_AL_PF_AGE_LT23_EXP_GE2",
      "value": 2408.44
    },
    {
      "cell_id": "D3_AL_PF_AGE_GE23_EXP_LT2",
      "value": 1702.84
    },
    {
      "cell_id": "D3_AL_PF_AGE_GE23_EXP_GE2",
      "value": 1600.67
    },
    {
      "cell_id": "D3_AL_PJ",
      "value": 2128.56
    },
    {
      "cell_id": "E1_CH_PF_AGE_LT23_EXP_LT2",
      "value": 453.12
    },
    {
      "cell_id": "E1_CH_PF_AGE_LT23_EXP_GE2",
      "value": 336.09
    },
    {
      "cell_id": "E1_CH_PF_AGE_GE23_EXP_LT2",
      "value": 300.08
    },
    {
      "cell_id": "E1_CH_PF_AGE_GE23_EXP_GE2",
      "value": 282.08
    },
    {
      "cell_id": "E1_CH_PJ",
      "value": 375.1
    },
    {
      "cell_id": "E1_AL_PF_AGE_LT23_EXP_LT2",
      "value": 233.75
    },
    {
      "cell_id": "E1_AL_PF_AGE_LT23_EXP_GE2",
      "value": 173.38
    },
    {
      "cell_id": "E1_AL_PF_AGE_GE23_EXP_LT2",
      "value": 154.8
    },
    {
      "cell_id": "E1_AL_PF_AGE_GE23_EXP_GE2",
      "value": 145.52
    },
    {
      "cell_id": "E1_AL_PJ",
      "value": 193.51
    },
    {
      "cell_id": "E2_CH_PF_AGE_LT23_EXP_LT2",
      "value": 723.76
    },
    {
      "cell_id": "E2_CH_PF_AGE_LT23_EXP_GE2",
      "value": 590.61
    },
    {
      "cell_id": "E2_CH_PF_AGE_GE23_EXP_LT2",
      "value": 378.95
    },
    {
      "cell_id": "E2_CH_PF_AGE_GE23_EXP_GE2",
      "value": 260.38
    },
    {
      "cell_id": "E2_CH_PJ",
      "value": 416.33
    },
    {
      "cell_id": "E2_AL_PF_AGE_LT23_EXP_LT2",
      "value": 398.35
    },
    {
      "cell_id": "E2_AL_PF_AGE_LT23_EXP_GE2",
      "value": 325.07
    },
    {
      "cell_id": "E2_AL_PF_AGE_GE23_EXP_LT2",
      "value": 208.57
    },
    {
      "cell_id": "E2_AL_PF_AGE_GE23_EXP_GE2",
      "value": 134.32
    },
    {
      "cell_id": "E2_AL_PJ",
      "value": 229.15
    }
  ]
}